docs/source/conf.py
docs/source/examples/plot_aequilibrae_example.py
docs/source/examples/plot_general_example.py
mapmatcher/__init__.py
mapmatcher/examples.py
mapmatcher/linebearing.py
mapmatcher/map_matcher.py
mapmatcher/network.py
mapmatcher/parameters.py
mapmatcher/run_chunk.py
mapmatcher/stop_finder.py
mapmatcher/trip.py
mapmatcher/example_data/traces_nauru.csv
mapmatcher-0.7.1.dist-info/METADATA
mapmatcher-0.7.1.dist-info/WHEEL
mapmatcher-0.7.1.dist-info/top_level.txt
mapmatcher-0.7.1.dist-info/RECORD
